madhur/core.py
madhur-0.1.0.dist-info/METADATA
madhur-0.1.0.dist-info/WHEEL
madhur-0.1.0.dist-info/top_level.txt
madhur-0.1.0.dist-info/RECORD
