Metadata-Version: 2.4
Name: madhur
Version: 0.1.0
Summary: My custom Python library
Author-email: Madhur <madhur@gmail.com>
License: MIT
